{
    "192345151618809857": [
        {
            "item_id": "719955",
            "enhancement_level": "5",
            "item_name": "Dahn's Gloves"
        }
    ],
    "91891869105016832": [
        {
            "item_id": "11653",
            "enhancement_level": "5",
            "item_name": "Deboreka Necklace"
        },
        {
            "item_id": "12276",
            "enhancement_level": "5",
            "item_name": "Deboreka Belt"
        },
        {
            "item_id": "11882",
            "enhancement_level": "5",
            "item_name": "Deboreka Earring"
        }
    ]
}